MANIFEST.in
setup.py
nmaptocsv/README.md
nmaptocsv/__init__.py
nmaptocsv/nmaptocsv.py
nmaptocsv/requirements.txt
nmaptocsv.egg-info/PKG-INFO
nmaptocsv.egg-info/SOURCES.txt
nmaptocsv.egg-info/dependency_links.txt
nmaptocsv.egg-info/entry_points.txt
nmaptocsv.egg-info/requires.txt
nmaptocsv.egg-info/top_level.txt