Metadata-Version: 2.1
Name: nmaptocsv
Version: 1.6
Summary: A simple python script to convert Nmap output to CSV
Home-page: https://github.com/maaaaz/nmaptocsv
Author: Thomas D.
Author-email: tdebize@mail.com
License: LGPL
Keywords: nmap scan output csv gnmap xml
Platform: UNKNOWN
Classifier: Topic :: Security
Classifier: Development Status :: 5 - Production/Stable
Classifier: Intended Audience :: Information Technology
Classifier: License :: OSI Approved :: GNU Library or Lesser General Public License (LGPL)
Classifier: Programming Language :: Python :: 3
Classifier: Programming Language :: Python :: 2.7
Requires-Python: >=2.7
